{
    "##": [
        "name:ZSNES",
        "author:zsKnight, -Demo-, and Pharos",
        "cmd:%BIN% %ROM%",
        "logo:https://consolo.is.cc/images/emuDownloadCenter/hooks/zsnes/emulator_logo.png",
        "screenshot:https://consolo.is.cc/images/emuDownloadCenter/hooks/zsnes/emulator_screen_01.jpg",
        "screenshots:https://cdn.emulationking.com/wp-content/uploads/2014/05/zsnes-SNES-Emulator-Pic-01.png,https://cdn.emulationking.com/wp-content/uploads/2014/05/zsnes-SNES-Emulator-Pic-02.jpg,https://cdn.emulationking.com/wp-content/uploads/2014/05/zsnes-SNES-Emulator-Pic-03.jpg,https://cdn.emulationking.com/wp-content/uploads/2014/05/zsnes-SNES-Emulator-Pic-04.jpg,https://cdn.emulationking.com/wp-content/uploads/2014/05/zsnes-SNES-Emulator-Pic-05.jpg,https://cdn.emulationking.com/wp-content/uploads/2014/05/zsnes-SNES-Emulator-Pic-06.jpg"
    ],
    "version": "1.51",
    "description": "zsnes is a SNES emulator that suffers from low accuracy when compared to higan and snes9x. Most of znes’s development focused on achieving portability and performance, with the bulk of the emulator being written in x86 assembly.",
    "homepage": "http://www.zsnes.com/",
    "license": "GPL-2.0-only",
    "url": "https://consolo.is.cc/emu/zsnes/1.51.7z",
    "hash": "3efa10a3d3204d767f40408d70934ca2833084609671e6db102892c1e6d563c1",
    "bin": [
        "zsnesw.exe"
    ],
    "architecture": {
        "32bit": {
            "url": "http://www.zsnes.com/zsnes_win32_1_51.zip",
            "hash": "sha256:ecaa114c62cbb7b3a1a03072b2f54dc0138a92f84c6d84d89e35ee12c8c7ec03"
        },
        "64bit": {
            "url": "http://www.zsnes.com/zsnes_win64_1_51.zip",
            "hash": "sha256:8146c8d06483c0d39f3dc2d4c4f0de4e16af9d4b18c294fcdf7bbf08b4d9887f"
        }
    },
    "checkver": {
        "url": "http://www.zsnes.com/",
        "regex": "<a href=\"http://www.zsnes.com/files/[^\"]+\">Download ZSNES ([0-9\\.]+)</a>"
    },
    "autoupdate": {
        "script": "zsnes.exe --version",
        "url": "http://www.zsnes.com/",
        "regex": "<a href=\"http://www.zsnes.com/files/[^\"]+\">Download ZSNES ([0-9\\.]+)</a>"
    }
}