{
    "##": [
        "name:DobieStation"
    ],
    "version": "",
    "description": "A young PS2 emulator with plans for an optimized Android port, as well as a fast, accurate, and easy-to-use PC port. A large portion of the PS2's library can boot or get to menus. Some titles can even go in-game, including high-profile ones such as Final Fantasy X and Shadow of the Colossus. Not intended for general use.",
    "homepage": null,
    "license": "",
    "url": "",
    "hash": "0220f27cc32b92c2c9cc909e4704873e155cd78e88f77d802f7a9945e1ba74f3",
    "bin": []
}
